tempmailwrapper/__init__.py
tempmailwrapper/tempmailwrapper.py
tempmailwrapper-0.0.3.dist-info/LICENSE
tempmailwrapper-0.0.3.dist-info/METADATA
tempmailwrapper-0.0.3.dist-info/WHEEL
tempmailwrapper-0.0.3.dist-info/top_level.txt
tempmailwrapper-0.0.3.dist-info/RECORD
