Metadata-Version: 2.1
Name: tempmailwrapper
Version: 0.0.3
Summary: API wrapper for Temp Mail API.
Home-page: https://github.com/Jimballoons/tempmailwrapper
Author: Jimballoons
Author-email: jimballoonsgit@gmail.com
License: UNKNOWN
Download-URL: https://github.com/Jimballoons/tempmailwrapper/archive/refs/tags/0.0.3.tar.gz
Keywords: python,tempmail,temporary,email,wrapper
Platform: UNKNOWN
Classifier: Development Status :: 1 - Planning
Classifier: Intended Audience :: Developers
Classifier: Programming Language :: Python :: 3
Classifier: Operating System :: Unix
Classifier: Operating System :: MacOS :: MacOS X
Classifier: Operating System :: Microsoft :: Windows
Requires-Dist: requests
